cappy/__init__.py
cappy/cpy.py
cappy/cpy_cv2.py
cappy/windowdata.py
CapPy_Python-0.0.6.dist-info/LICENSE
CapPy_Python-0.0.6.dist-info/METADATA
CapPy_Python-0.0.6.dist-info/WHEEL
CapPy_Python-0.0.6.dist-info/top_level.txt
CapPy_Python-0.0.6.dist-info/RECORD
