Metadata-Version: 2.1
Name: CapPy-Python
Version: 0.0.6
Summary: Python package for easy window capturing
Home-page: https://github.com/GE0NE/CapPy
Author: GEONE
Author-email: geonegames@gmail.com
License: UNKNOWN
Platform: UNKNOWN
Classifier: Development Status :: 3 - Alpha
Classifier: Programming Language :: Python :: 3
Classifier: License :: OSI Approved :: MIT License
Classifier: Operating System :: Microsoft :: Windows
Classifier: Operating System :: Microsoft :: Windows :: Windows 10
Classifier: Operating System :: Microsoft :: Windows :: Windows 8.1
Classifier: Operating System :: Microsoft :: Windows :: Windows 8
Classifier: Operating System :: Microsoft :: Windows :: Windows 7
Classifier: Topic :: Software Development :: Libraries :: Python Modules
Requires-Dist: numpy (>=1.15.0)
Requires-Dist: pillow (>=5.0.0)
Requires-Dist: pywin32 (>=224)
Requires-Dist: psutil (>=5.4.3)
